exposure/__init__.py
exposure/utils.py
exposure-0.1.1.dist-info/WHEEL
exposure-0.1.1.dist-info/METADATA
exposure-0.1.1.dist-info/RECORD
