Metadata-Version: 2.1
Name: exposure
Version: 0.1.1
Summary: tool for compute with exposure settings and metrics for cameras
Home-page: https://github.com/mrijken/exposure
License: MIT
Author: Marc Rijken
Author-email: marc@rijken.org
Requires-Python: >=3.6,<4.0
Classifier: License :: OSI Approved :: MIT License
Classifier: Programming Language :: Python :: 3
Classifier: Programming Language :: Python :: 3.6
Classifier: Programming Language :: Python :: 3.7
Classifier: Programming Language :: Python :: 3.8
Classifier: Programming Language :: Python :: 3.9
Project-URL: Repository, https://github.com/mrijken/exposure
